<annotation verified="yes">
	<folder>Image</folder>
	<filename>07_24-06_IMG_LOG__CAM_2_20240113_192247_466.jpg</filename>
	<path>C:\Users\AUO1HC\Bosch Group\HcP_AOI_AI - AI Model Development - Documents\AI Model Development\Data\Train\Image\07_24-06_IMG_LOG__CAM_2_20240113_192247_466.jpg</path>
	<source>
		<database>Unknown</database>
	</source>
	<size>
		<width>1296</width>
		<height>600</height>
		<depth>1</depth>
	</size>
	<segmented>0</segmented>
	<object>
		<name>oil</name>
		<pose>Unspecified</pose>
		<truncated>0</truncated>
		<difficult>0</difficult>
		<bndbox>
			<xmin>315</xmin>
			<ymin>244</ymin>
			<xmax>373</xmax>
			<ymax>268</ymax>
		</bndbox>
	</object>
	<object>
		<name>oil</name>
		<pose>Unspecified</pose>
		<truncated>0</truncated>
		<difficult>0</difficult>
		<bndbox>
			<xmin>272</xmin>
			<ymin>239</ymin>
			<xmax>299</xmax>
			<ymax>253</ymax>
		</bndbox>
	</object>
	<object>
		<name>oil</name>
		<pose>Unspecified</pose>
		<truncated>0</truncated>
		<difficult>0</difficult>
		<bndbox>
			<xmin>76</xmin>
			<ymin>258</ymin>
			<xmax>205</xmax>
			<ymax>310</ymax>
		</bndbox>
	</object>
	<object>
		<name>abriss</name>
		<pose>Unspecified</pose>
		<truncated>0</truncated>
		<difficult>0</difficult>
		<bndbox>
			<xmin>320</xmin>
			<ymin>230</ymin>
			<xmax>335</xmax>
			<ymax>242</ymax>
		</bndbox>
	</object>
	<object>
		<name>abriss</name>
		<pose>Unspecified</pose>
		<truncated>0</truncated>
		<difficult>0</difficult>
		<bndbox>
			<xmin>278</xmin>
			<ymin>229</ymin>
			<xmax>293</xmax>
			<ymax>238</ymax>
		</bndbox>
	</object>
</annotation>