<annotation>
	<folder>Image_raw</folder>
	<filename>07_24-06_IMG_LOG__CAM_2_20240120_151654_584.jpg</filename>
	<path>C:\Users\AI_PRO_DESK\OneDrive - boschtga\Partition_Local\AI@AOI\Pre_data\Image_raw\07_24-06_IMG_LOG__CAM_2_20240120_151654_584.jpg</path>
	<source>
		<database>Unknown</database>
	</source>
	<size>
		<width>1296</width>
		<height>600</height>
		<depth>1</depth>
	</size>
	<segmented>0</segmented>
	<object>
		<name>abriss</name>
		<pose>Unspecified</pose>
		<truncated>0</truncated>
		<difficult>0</difficult>
		<bndbox>
			<xmin>31</xmin>
			<ymin>255</ymin>
			<xmax>87</xmax>
			<ymax>274</ymax>
		</bndbox>
	</object>
	<object>
		<name>abriss</name>
		<pose>Unspecified</pose>
		<truncated>0</truncated>
		<difficult>0</difficult>
		<bndbox>
			<xmin>103</xmin>
			<ymin>257</ymin>
			<xmax>195</xmax>
			<ymax>267</ymax>
		</bndbox>
	</object>
	<object>
		<name>abriss</name>
		<pose>Unspecified</pose>
		<truncated>0</truncated>
		<difficult>0</difficult>
		<bndbox>
			<xmin>200</xmin>
			<ymin>260</ymin>
			<xmax>444</xmax>
			<ymax>277</ymax>
		</bndbox>
	</object>
	<object>
		<name>abriss</name>
		<pose>Unspecified</pose>
		<truncated>0</truncated>
		<difficult>0</difficult>
		<bndbox>
			<xmin>523</xmin>
			<ymin>272</ymin>
			<xmax>550</xmax>
			<ymax>278</ymax>
		</bndbox>
	</object>
</annotation>
